{
  "$schema": "https://dev.office.com/json-schemas/spfx/client-side-web-part-manifest.schema.json",
  "id": "bcc46667-5dec-4830-82ea-ea37ec2f1a9d",
  "alias": "HelloworldReactWebPart",
  "componentType": "WebPart",

  // The "*" signifies that the version should be taken from the package.json
  "version": "*",
  "manifestVersion": 2,

  // If true, the component can only be installed on sites where Custom Script is allowed.
  // Components that allow authors to embed arbitrary script code should set this to true.
  // https://support.office.com/en-us/article/Turn-scripting-capabilities-on-or-off-1f2c515f-5d7e-448a-9fd7-835da935584f
  "requiresCustomScript": false,

  "preconfiguredEntries": [{
    "groupId": "bcc46667-5dec-4830-82ea-ea37ec2f1a9d",
    "group": { "default": "Under Development" },
    "title": { "default": "HelloworldReact" },
    "description": { "default": "Helloworld React description" },
    "officeFabricIconFontName": "Page",
    "properties": {
      "description": "HelloworldReact"
    }
  }]
}
